LICENSE
MANIFEST.in
README.md
requirements.txt
setup.cfg
setup.py
display_flex/__init__.py
display_flex/__meta__.py
display_flex/css_flexbox.py
display_flex/wrapper.py
display_flex.egg-info/PKG-INFO
display_flex.egg-info/SOURCES.txt
display_flex.egg-info/dependency_links.txt
display_flex.egg-info/not-zip-safe
display_flex.egg-info/requires.txt
display_flex.egg-info/top_level.txt