Metadata-Version: 1.1
Name: display-flex
Version: 0.2.2
Summary: Improved IPython.display.display with CSS Flexbox layout
Home-page: https://gitlab.com/oscar6echo/display-flex
Author: oscar6echo
Author-email: olivier.borderies@gmail.com
License: MIT
Download-URL: https://gitlab.com/oscar6echo/display-flex/repository/archive.tar.gz?ref=0.2.2
Keywords: python,display,html,css,flexbox
Platform: UNKNOWN
Classifier: Development Status :: 4 - Beta
Classifier: License :: OSI Approved :: MIT License
Classifier: Programming Language :: Python :: 2.7
Classifier: Programming Language :: Python :: 3.5
Classifier: Programming Language :: Python :: 3.6
